app_utils/__init__.py
app_utils/_app_settings.py
app_utils/admin.py
app_utils/allianceauth.py
app_utils/app_settings.py
app_utils/caching.py
app_utils/database.py
app_utils/datetime.py
app_utils/django.py
app_utils/esi.py
app_utils/esi_testing.py
app_utils/helpers.py
app_utils/json.py
app_utils/logging.py
app_utils/messages.py
app_utils/scripts.py
app_utils/testdata_factories.py
app_utils/testing.py
app_utils/testrunners.py
app_utils/urls.py
app_utils/views.py
allianceauth_app_utils-1.30.0.dist-info/licenses/LICENSE
allianceauth_app_utils-1.30.0.dist-info/WHEEL
allianceauth_app_utils-1.30.0.dist-info/METADATA
allianceauth_app_utils-1.30.0.dist-info/RECORD
