Metadata-Version: 2.4
Name: allianceauth-app-utils
Version: 1.30.0
Summary: Commonly used utilities and helpers for rapid development of Alliance Auth apps.
Author-email: Erik Kalkoken <kalkoken87@gmail.com>
Requires-Python: >=3.8
Classifier: Environment :: Web Environment
Classifier: Framework :: Django
Classifier: Framework :: Django :: 4.0
Classifier: Framework :: Django :: 4.2
Classifier: Intended Audience :: Developers
Classifier: License :: OSI Approved :: MIT License
Classifier: Operating System :: OS Independent
Classifier: Programming Language :: Python
Classifier: Programming Language :: Python :: 3.8
Classifier: Programming Language :: Python :: 3.9
Classifier: Programming Language :: Python :: 3.10
Classifier: Programming Language :: Python :: 3.11
Classifier: Programming Language :: Python :: 3.12
Classifier: Topic :: Internet :: WWW/HTTP
Classifier: Topic :: Internet :: WWW/HTTP :: Dynamic Content
License-File: LICENSE
Requires-Dist: allianceauth>=3,<5
Requires-Dist: requests
Project-URL: Changelog, https://gitlab.com/ErikKalkoken/allianceauth-app-utils/-/blob/master/CHANGELOG.md
Project-URL: Documentation, https://allianceauth-app-utils.readthedocs.io/en/latest/
Project-URL: Homepage, https://gitlab.com/ErikKalkoken/allianceauth-app-utils
Project-URL: Source, https://gitlab.com/ErikKalkoken/allianceauth-app-utils
Project-URL: Tracker, https://gitlab.com/ErikKalkoken/allianceauth-app-utils/-/issues
